<?xml version="1.0" encoding="UTF-8"?><embeddedOutputs><metaData><evaluationState>manual</evaluationState><layoutState>code</layoutState><outputStatus>error</outputStatus><splitterState><proportion>0.4</proportion></splitterState></metaData><outputArray type="array"><element><type>matrix</type><outputData><header></header><name>q_gps</name><varSize>3×250</varSize><rows>3</rows><columns>250</columns><varType>double</varType><value>     0     0     0     0     0     0     0     0     0     0     0     0     0     0     0     0     0     0     0     0     0     0     0     0     0     0     0     0     0     0     0     0     0     0     0     0     0     0     0     0     0     0     0     0     0     0     0     0     0     0
     0     0     0     0     0     0     0     0     0     0     0     0     0     0     0     0     0     0     0     0     0     0     0     0     0     0     0     0     0     0     0     0     0     0     0     0     0     0     0     0     0     0     0     0     0     0     0     0     0     0
     0     0     0     0     0     0     0     0     0     0     0     0     0     0     0     0     0     0     0     0     0     0     0     0     0     0     0     0     0     0     0     0     0     0     0     0     0     0     0     0     0     0     0     0     0     0     0     0     0     0
</value><type>double</type><subtype>double</subtype><prepopulatedData>[[{"value":"{\"value\":\"0\"}"},{"value":"{\"value\":\"0\"}"},{"value":"{\"value\":\"0\"}"},{"value":"{\"value\":\"0\"}"},{"value":"{\"value\":\"0\"}"},{"value":"{\"value\":\"0\"}"},{"value":"{\"value\":\"0\"}"},{"value":"{\"value\":\"0\"}"},{"value":"{\"value\":\"0\"}"},{"value":"{\"value\":\"0\"}"},{"value":"{\"value\":\"0\"}"},{"value":"{\"value\":\"0\"}"},{"value":"{\"value\":\"0\"}"},{"value":"{\"value\":\"0\"}"},{"value":"{\"value\":\"0\"}"},{"value":"{\"value\":\"0\"}"},{"value":"{\"value\":\"0\"}"},{"value":"{\"value\":\"0\"}"},{"value":"{\"value\":\"0\"}"},{"value":"{\"value\":\"0\"}"},{"value":"{\"value\":\"0\"}"},{"value":"{\"value\":\"0\"}"},{"value":"{\"value\":\"0\"}"},{"value":"{\"value\":\"0\"}"},{"value":"{\"value\":\"0\"}"},{"value":"{\"value\":\"0\"}"},{"value":"{\"value\":\"0\"}"},{"value":"{\"value\":\"0\"}"},{"value":"{\"value\":\"0\"}"},{"value":"{\"value\":\"0\"}"}]]</prepopulatedData></outputData><lineNumbers type="array"><element>11</element></lineNumbers></element><element><type>variable</type><outputData><name>count</name><value>1</value><rows>1</rows><columns>1</columns></outputData><lineNumbers type="array"><element>14</element></lineNumbers></element><element><type>matrix</type><outputData><header></header><name>W</name><varSize>2×2</varSize><rows>2</rows><columns>2</columns><varType>double</varType><value>    1.8817    0.0632
    0.0632    2.1384
</value><type>double</type><savedData>[["1.8817","0.0632"],["0.0632","2.1384"]]</savedData><subtype>double</subtype><prepopulatedData>[[{"value":"{\"value\":\"1.8817\"}"},{"value":"{\"value\":\"0.0632\"}"}]]</prepopulatedData></outputData><lineNumbers type="array"><element>25</element></lineNumbers></element><element><type>matrix</type><outputData><header></header><name>V</name><varSize>2×2</varSize><rows>2</rows><columns>2</columns><varType>double</varType><value>    0.2590    0.0010
    0.0010    0.0625
</value><type>double</type><subtype>double</subtype><prepopulatedData>[[{"value":"{\"value\":\"0.2590\"}"},{"value":"{\"value\":\"0.0010\"}"}]]</prepopulatedData></outputData><lineNumbers type="array"><element>48</element></lineNumbers></element></outputArray><regionArray type="array"><element><code><sectionBreak>true</sectionBreak><endOfSection>false</endOfSection><regionNumber>0</regionNumber></code><startLine>8</startLine><endLine>8</endLine><outputIndexes type="array"/></element><element><code><sectionBreak>false</sectionBreak><endOfSection>false</endOfSection><regionNumber>1</regionNumber></code><startLine>10</startLine><endLine>10</endLine><outputIndexes type="array"><element>0</element></outputIndexes></element><element><code><sectionBreak>false</sectionBreak><endOfSection>false</endOfSection><regionNumber>2</regionNumber></code><startLine>11</startLine><endLine>11</endLine><outputIndexes type="array"/></element><element><code><sectionBreak>false</sectionBreak><endOfSection>false</endOfSection><regionNumber>3</regionNumber></code><startLine>13</startLine><endLine>13</endLine><outputIndexes type="array"><element>1</element></outputIndexes></element><element><code><sectionBreak>false</sectionBreak><endOfSection>false</endOfSection><regionNumber>4</regionNumber></code><startLine>14</startLine><endLine>21</endLine><outputIndexes type="array"/></element><element><code><sectionBreak>false</sectionBreak><endOfSection>false</endOfSection><regionNumber>5</regionNumber></code><startLine>23</startLine><endLine>23</endLine><outputIndexes type="array"/></element><element><code><sectionBreak>false</sectionBreak><endOfSection>false</endOfSection><regionNumber>6</regionNumber></code><startLine>24</startLine><endLine>24</endLine><outputIndexes type="array"><element>2</element></outputIndexes></element><element><code><sectionBreak>false</sectionBreak><endOfSection>false</endOfSection><regionNumber>7</regionNumber></code><startLine>27</startLine><endLine>27</endLine><outputIndexes type="array"/></element><element><code><sectionBreak>false</sectionBreak><endOfSection>false</endOfSection><regionNumber>8</regionNumber></code><startLine>28</startLine><endLine>28</endLine><outputIndexes type="array"/></element><element><code><sectionBreak>false</sectionBreak><endOfSection>false</endOfSection><regionNumber>9</regionNumber></code><startLine>30</startLine><endLine>47</endLine><outputIndexes type="array"/></element><element><code><sectionBreak>false</sectionBreak><endOfSection>true</endOfSection><regionNumber>10</regionNumber></code><startLine>48</startLine><endLine>48</endLine><outputIndexes type="array"><element>3</element></outputIndexes></element></regionArray></embeddedOutputs>